<api>
<package name="com.amadeus"
>
<class name="Amadeus"
 extends="com.amadeus.HTTPClient"
 abstract="false"
 static="false"
 final="false"
 deprecated="not deprecated"
 visibility="public"
>
<method name="builder"
 return="com.amadeus.Configuration"
 abstract="false"
 native="false"
 synchronized="false"
 static="true"
 final="false"
 deprecated="not deprecated"
 visibility="public"
>
<parameter name="clientId" type="java.lang.String">
</parameter>
<parameter name="clientSecret" type="java.lang.String">
</parameter>
</method>
<method name="builder"
 return="com.amadeus.Configuration"
 abstract="false"
 native="false"
 synchronized="false"
 static="true"
 final="false"
 deprecated="not deprecated"
 visibility="public"
>
<parameter name="environment" type="java.util.Map&lt;java.lang.String, java.lang.String&gt;">
</parameter>
</method>
<field name="VERSION"
 type="java.lang.String"
 transient="false"
 volatile="false"
 value="&quot;1.1.0&quot;"
 static="true"
 final="true"
 deprecated="not deprecated"
 visibility="public"
>
</field>
<field name="referenceData"
 type="com.amadeus.ReferenceData"
 transient="false"
 volatile="false"
 static="false"
 final="false"
 deprecated="not deprecated"
 visibility="public"
>
</field>
<field name="shopping"
 type="com.amadeus.Shopping"
 transient="false"
 volatile="false"
 static="false"
 final="false"
 deprecated="not deprecated"
 visibility="public"
>
</field>
<field name="travel"
 type="com.amadeus.Travel"
 transient="false"
 volatile="false"
 static="false"
 final="false"
 deprecated="not deprecated"
 visibility="public"
>
</field>
</class>
<class name="Configuration"
 extends="java.lang.Object"
 abstract="false"
 static="false"
 final="false"
 deprecated="not deprecated"
 visibility="public"
>
<method name="build"
 return="com.amadeus.Amadeus"
 abstract="false"
 native="false"
 synchronized="false"
 static="false"
 final="false"
 deprecated="not deprecated"
 visibility="public"
>
<exception name="NullPointerException" type="java.lang.NullPointerException">
</exception>
</method>
<method name="getClientId"
 return="java.lang.String"
 abstract="false"
 native="false"
 synchronized="false"
 static="false"
 final="false"
 deprecated="not deprecated"
 visibility="public"
>
</method>
<method name="getClientSecret"
 return="java.lang.String"
 abstract="false"
 native="false"
 synchronized="false"
 static="false"
 final="false"
 deprecated="not deprecated"
 visibility="public"
>
</method>
<method name="getCustomAppId"
 return="java.lang.String"
 abstract="false"
 native="false"
 synchronized="false"
 static="false"
 final="false"
 deprecated="not deprecated"
 visibility="public"
>
</method>
<method name="getCustomAppVersion"
 return="java.lang.String"
 abstract="false"
 native="false"
 synchronized="false"
 static="false"
 final="false"
 deprecated="not deprecated"
 visibility="public"
>
</method>
<method name="getHost"
 return="java.lang.String"
 abstract="false"
 native="false"
 synchronized="false"
 static="false"
 final="false"
 deprecated="not deprecated"
 visibility="public"
>
</method>
<method name="getHostname"
 return="java.lang.String"
 abstract="false"
 native="false"
 synchronized="false"
 static="false"
 final="false"
 deprecated="not deprecated"
 visibility="public"
>
</method>
<method name="getLogLevel"
 return="java.lang.String"
 abstract="false"
 native="false"
 synchronized="false"
 static="false"
 final="false"
 deprecated="not deprecated"
 visibility="public"
>
</method>
<method name="getLogger"
 return="java.util.logging.Logger"
 abstract="false"
 native="false"
 synchronized="false"
 static="false"
 final="false"
 deprecated="not deprecated"
 visibility="public"
>
</method>
<method name="getPort"
 return="int"
 abstract="false"
 native="false"
 synchronized="false"
 static="false"
 final="false"
 deprecated="not deprecated"
 visibility="public"
>
</method>
<method name="isSsl"
 return="boolean"
 abstract="false"
 native="false"
 synchronized="false"
 static="false"
 final="false"
 deprecated="not deprecated"
 visibility="public"
>
</method>
<method name="setCustomAppId"
 return="com.amadeus.Configuration"
 abstract="false"
 native="false"
 synchronized="false"
 static="false"
 final="false"
 deprecated="not deprecated"
 visibility="public"
>
<parameter name="customAppId" type="java.lang.String">
</parameter>
</method>
<method name="setCustomAppVersion"
 return="com.amadeus.Configuration"
 abstract="false"
 native="false"
 synchronized="false"
 static="false"
 final="false"
 deprecated="not deprecated"
 visibility="public"
>
<parameter name="customAppVersion" type="java.lang.String">
</parameter>
</method>
<method name="setHost"
 return="com.amadeus.Configuration"
 abstract="false"
 native="false"
 synchronized="false"
 static="false"
 final="false"
 deprecated="not deprecated"
 visibility="public"
>
<parameter name="host" type="java.lang.String">
</parameter>
</method>
<method name="setHostname"
 return="com.amadeus.Configuration"
 abstract="false"
 native="false"
 synchronized="false"
 static="false"
 final="false"
 deprecated="not deprecated"
 visibility="public"
>
<parameter name="hostname" type="java.lang.String">
</parameter>
</method>
<method name="setLogLevel"
 return="com.amadeus.Configuration"
 abstract="false"
 native="false"
 synchronized="false"
 static="false"
 final="false"
 deprecated="not deprecated"
 visibility="public"
>
<parameter name="logLevel" type="java.lang.String">
</parameter>
</method>
<method name="setLogger"
 return="com.amadeus.Configuration"
 abstract="false"
 native="false"
 synchronized="false"
 static="false"
 final="false"
 deprecated="not deprecated"
 visibility="public"
>
<parameter name="logger" type="java.util.logging.Logger">
</parameter>
</method>
<method name="setPort"
 return="com.amadeus.Configuration"
 abstract="false"
 native="false"
 synchronized="false"
 static="false"
 final="false"
 deprecated="not deprecated"
 visibility="public"
>
<parameter name="port" type="int">
</parameter>
</method>
<method name="setSsl"
 return="com.amadeus.Configuration"
 abstract="false"
 native="false"
 synchronized="false"
 static="false"
 final="false"
 deprecated="not deprecated"
 visibility="public"
>
<parameter name="ssl" type="java.lang.Boolean">
</parameter>
</method>
</class>
<class name="Constants"
 extends="java.lang.Object"
 abstract="false"
 static="false"
 final="true"
 deprecated="not deprecated"
 visibility="public"
>
<field name="ACCEPT"
 type="java.lang.String"
 transient="false"
 volatile="false"
 value="&quot;Accept&quot;"
 static="true"
 final="true"
 deprecated="not deprecated"
 visibility="public"
>
</field>
<field name="ACCESS_TOKEN"
 type="java.lang.String"
 transient="false"
 volatile="false"
 value="&quot;access_token&quot;"
 static="true"
 final="true"
 deprecated="not deprecated"
 visibility="public"
>
</field>
<field name="AUTHORIZATION"
 type="java.lang.String"
 transient="false"
 volatile="false"
 value="&quot;Authorization&quot;"
 static="true"
 final="true"
 deprecated="not deprecated"
 visibility="public"
>
</field>
<field name="AUTH_URL"
 type="java.lang.String"
 transient="false"
 volatile="false"
 value="&quot;/v1/security/oauth2/token&quot;"
 static="true"
 final="true"
 deprecated="not deprecated"
 visibility="public"
>
</field>
<field name="CLIENT_CREDENTIALS"
 type="java.lang.String"
 transient="false"
 volatile="false"
 value="&quot;client_credentials&quot;"
 static="true"
 final="true"
 deprecated="not deprecated"
 visibility="public"
>
</field>
<field name="CLIENT_ID"
 type="java.lang.String"
 transient="false"
 volatile="false"
 value="&quot;client_id&quot;"
 static="true"
 final="true"
 deprecated="not deprecated"
 visibility="public"
>
</field>
<field name="CLIENT_SECRET"
 type="java.lang.String"
 transient="false"
 volatile="false"
 value="&quot;client_secret&quot;"
 static="true"
 final="true"
 deprecated="not deprecated"
 visibility="public"
>
</field>
<field name="CONTENT_TYPE"
 type="java.lang.String"
 transient="false"
 volatile="false"
 value="&quot;Content-Type&quot;"
 static="true"
 final="true"
 deprecated="not deprecated"
 visibility="public"
>
</field>
<field name="EXPIRES_IN"
 type="java.lang.String"
 transient="false"
 volatile="false"
 value="&quot;expires_in&quot;"
 static="true"
 final="true"
 deprecated="not deprecated"
 visibility="public"
>
</field>
<field name="FIRST"
 type="java.lang.String"
 transient="false"
 volatile="false"
 value="&quot;first&quot;"
 static="true"
 final="true"
 deprecated="not deprecated"
 visibility="public"
>
</field>
<field name="GET"
 type="java.lang.String"
 transient="false"
 volatile="false"
 value="&quot;GET&quot;"
 static="true"
 final="true"
 deprecated="not deprecated"
 visibility="public"
>
</field>
<field name="GRANT_TYPE"
 type="java.lang.String"
 transient="false"
 volatile="false"
 value="&quot;grant_type&quot;"
 static="true"
 final="true"
 deprecated="not deprecated"
 visibility="public"
>
</field>
<field name="HTTP"
 type="java.lang.String"
 transient="false"
 volatile="false"
 value="&quot;http&quot;"
 static="true"
 final="true"
 deprecated="not deprecated"
 visibility="public"
>
</field>
<field name="HTTPS"
 type="java.lang.String"
 transient="false"
 volatile="false"
 value="&quot;https&quot;"
 static="true"
 final="true"
 deprecated="not deprecated"
 visibility="public"
>
</field>
<field name="LAST"
 type="java.lang.String"
 transient="false"
 volatile="false"
 value="&quot;last&quot;"
 static="true"
 final="true"
 deprecated="not deprecated"
 visibility="public"
>
</field>
<field name="NEXT"
 type="java.lang.String"
 transient="false"
 volatile="false"
 value="&quot;next&quot;"
 static="true"
 final="true"
 deprecated="not deprecated"
 visibility="public"
>
</field>
<field name="POST"
 type="java.lang.String"
 transient="false"
 volatile="false"
 value="&quot;POST&quot;"
 static="true"
 final="true"
 deprecated="not deprecated"
 visibility="public"
>
</field>
<field name="PREVIOUS"
 type="java.lang.String"
 transient="false"
 volatile="false"
 value="&quot;previous&quot;"
 static="true"
 final="true"
 deprecated="not deprecated"
 visibility="public"
>
</field>
<field name="USER_AGENT"
 type="java.lang.String"
 transient="false"
 volatile="false"
 value="&quot;User-Agent&quot;"
 static="true"
 final="true"
 deprecated="not deprecated"
 visibility="public"
>
</field>
</class>
<class name="HTTPClient"
 extends="java.lang.Object"
 abstract="false"
 static="false"
 final="false"
 deprecated="not deprecated"
 visibility="public"
>
<method name="first"
 return="com.amadeus.Response"
 abstract="false"
 native="false"
 synchronized="false"
 static="false"
 final="false"
 deprecated="not deprecated"
 visibility="public"
>
<parameter name="response" type="com.amadeus.Response">
</parameter>
<exception name="ResponseException" type="com.amadeus.exceptions.ResponseException">
</exception>
</method>
<method name="first"
 return="com.amadeus.resources.Resource[]"
 abstract="false"
 native="false"
 synchronized="false"
 static="false"
 final="false"
 deprecated="not deprecated"
 visibility="public"
>
<parameter name="resource" type="com.amadeus.resources.Resource">
</parameter>
<exception name="ResponseException" type="com.amadeus.exceptions.ResponseException">
</exception>
</method>
<method name="get"
 return="com.amadeus.Response"
 abstract="false"
 native="false"
 synchronized="false"
 static="false"
 final="false"
 deprecated="not deprecated"
 visibility="public"
>
<parameter name="path" type="java.lang.String">
</parameter>
<exception name="ResponseException" type="com.amadeus.exceptions.ResponseException">
</exception>
</method>
<method name="get"
 return="com.amadeus.Response"
 abstract="false"
 native="false"
 synchronized="false"
 static="false"
 final="false"
 deprecated="not deprecated"
 visibility="public"
>
<parameter name="path" type="java.lang.String">
</parameter>
<parameter name="params" type="com.amadeus.Params">
</parameter>
<exception name="ResponseException" type="com.amadeus.exceptions.ResponseException">
</exception>
</method>
<method name="getConfiguration"
 return="com.amadeus.Configuration"
 abstract="false"
 native="false"
 synchronized="false"
 static="false"
 final="false"
 deprecated="not deprecated"
 visibility="public"
>
</method>
<method name="last"
 return="com.amadeus.Response"
 abstract="false"
 native="false"
 synchronized="false"
 static="false"
 final="false"
 deprecated="not deprecated"
 visibility="public"
>
<parameter name="response" type="com.amadeus.Response">
</parameter>
<exception name="ResponseException" type="com.amadeus.exceptions.ResponseException">
</exception>
</method>
<method name="last"
 return="com.amadeus.resources.Resource[]"
 abstract="false"
 native="false"
 synchronized="false"
 static="false"
 final="false"
 deprecated="not deprecated"
 visibility="public"
>
<parameter name="resource" type="com.amadeus.resources.Resource">
</parameter>
<exception name="ResponseException" type="com.amadeus.exceptions.ResponseException">
</exception>
</method>
<method name="next"
 return="com.amadeus.Response"
 abstract="false"
 native="false"
 synchronized="false"
 static="false"
 final="false"
 deprecated="not deprecated"
 visibility="public"
>
<parameter name="response" type="com.amadeus.Response">
</parameter>
<exception name="ResponseException" type="com.amadeus.exceptions.ResponseException">
</exception>
</method>
<method name="next"
 return="com.amadeus.resources.Resource[]"
 abstract="false"
 native="false"
 synchronized="false"
 static="false"
 final="false"
 deprecated="not deprecated"
 visibility="public"
>
<parameter name="resource" type="com.amadeus.resources.Resource">
</parameter>
<exception name="ResponseException" type="com.amadeus.exceptions.ResponseException">
</exception>
</method>
<method name="post"
 return="com.amadeus.Response"
 abstract="false"
 native="false"
 synchronized="false"
 static="false"
 final="false"
 deprecated="not deprecated"
 visibility="public"
>
<parameter name="path" type="java.lang.String">
</parameter>
<exception name="ResponseException" type="com.amadeus.exceptions.ResponseException">
</exception>
</method>
<method name="post"
 return="com.amadeus.Response"
 abstract="false"
 native="false"
 synchronized="false"
 static="false"
 final="false"
 deprecated="not deprecated"
 visibility="public"
>
<parameter name="path" type="java.lang.String">
</parameter>
<parameter name="params" type="com.amadeus.Params">
</parameter>
<exception name="ResponseException" type="com.amadeus.exceptions.ResponseException">
</exception>
</method>
<method name="previous"
 return="com.amadeus.Response"
 abstract="false"
 native="false"
 synchronized="false"
 static="false"
 final="false"
 deprecated="not deprecated"
 visibility="public"
>
<parameter name="response" type="com.amadeus.Response">
</parameter>
<exception name="ResponseException" type="com.amadeus.exceptions.ResponseException">
</exception>
</method>
<method name="previous"
 return="com.amadeus.resources.Resource[]"
 abstract="false"
 native="false"
 synchronized="false"
 static="false"
 final="false"
 deprecated="not deprecated"
 visibility="public"
>
<parameter name="resource" type="com.amadeus.resources.Resource">
</parameter>
<exception name="ResponseException" type="com.amadeus.exceptions.ResponseException">
</exception>
</method>
</class>
<class name="Params"
 extends="java.util.HashMap"
 abstract="false"
 static="false"
 final="false"
 deprecated="not deprecated"
 visibility="public"
>
<method name="and"
 return="com.amadeus.Params"
 abstract="false"
 native="false"
 synchronized="false"
 static="false"
 final="false"
 deprecated="not deprecated"
 visibility="public"
>
<parameter name="key" type="java.lang.String">
</parameter>
<parameter name="value" type="java.lang.Object">
</parameter>
</method>
<method name="with"
 return="com.amadeus.Params"
 abstract="false"
 native="false"
 synchronized="false"
 static="true"
 final="false"
 deprecated="not deprecated"
 visibility="public"
>
<parameter name="key" type="java.lang.String">
</parameter>
<parameter name="value" type="java.lang.Object">
</parameter>
</method>
</class>
<class name="ReferenceData"
 extends="java.lang.Object"
 abstract="false"
 static="false"
 final="false"
 deprecated="not deprecated"
 visibility="public"
>
<method name="location"
 return="com.amadeus.referenceData.Location"
 abstract="false"
 native="false"
 synchronized="false"
 static="false"
 final="false"
 deprecated="not deprecated"
 visibility="public"
>
<parameter name="locationId" type="java.lang.String">
</parameter>
</method>
<field name="airlines"
 type="com.amadeus.referenceData.Airlines"
 transient="false"
 volatile="false"
 static="false"
 final="false"
 deprecated="not deprecated"
 visibility="public"
>
</field>
<field name="locations"
 type="com.amadeus.referenceData.Locations"
 transient="false"
 volatile="false"
 static="false"
 final="false"
 deprecated="not deprecated"
 visibility="public"
>
</field>
<field name="urls"
 type="com.amadeus.referenceData.Urls"
 transient="false"
 volatile="false"
 static="false"
 final="false"
 deprecated="not deprecated"
 visibility="public"
>
</field>
</class>
<class name="Request"
 extends="java.lang.Object"
 abstract="false"
 static="false"
 final="false"
 deprecated="not deprecated"
 visibility="public"
>
<method name="getAppId"
 return="java.lang.String"
 abstract="false"
 native="false"
 synchronized="false"
 static="false"
 final="false"
 deprecated="not deprecated"
 visibility="public"
>
</method>
<method name="getAppVersion"
 return="java.lang.String"
 abstract="false"
 native="false"
 synchronized="false"
 static="false"
 final="false"
 deprecated="not deprecated"
 visibility="public"
>
</method>
<method name="getBearerToken"
 return="java.lang.String"
 abstract="false"
 native="false"
 synchronized="false"
 static="false"
 final="false"
 deprecated="not deprecated"
 visibility="public"
>
</method>
<method name="getClientVersion"
 return="java.lang.String"
 abstract="false"
 native="false"
 synchronized="false"
 static="false"
 final="false"
 deprecated="not deprecated"
 visibility="public"
>
</method>
<method name="getConnection"
 return="java.net.HttpURLConnection"
 abstract="false"
 native="false"
 synchronized="false"
 static="false"
 final="false"
 deprecated="not deprecated"
 visibility="public"
>
</method>
<method name="getHeaders"
 return="java.util.HashMap&lt;java.lang.String, java.lang.String&gt;"
 abstract="false"
 native="false"
 synchronized="false"
 static="false"
 final="false"
 deprecated="not deprecated"
 visibility="public"
>
</method>
<method name="getHost"
 return="java.lang.String"
 abstract="false"
 native="false"
 synchronized="false"
 static="false"
 final="false"
 deprecated="not deprecated"
 visibility="public"
>
</method>
<method name="getLanguageVersion"
 return="java.lang.String"
 abstract="false"
 native="false"
 synchronized="false"
 static="false"
 final="false"
 deprecated="not deprecated"
 visibility="public"
>
</method>
<method name="getParams"
 return="com.amadeus.Params"
 abstract="false"
 native="false"
 synchronized="false"
 static="false"
 final="false"
 deprecated="not deprecated"
 visibility="public"
>
</method>
<method name="getPath"
 return="java.lang.String"
 abstract="false"
 native="false"
 synchronized="false"
 static="false"
 final="false"
 deprecated="not deprecated"
 visibility="public"
>
</method>
<method name="getPort"
 return="int"
 abstract="false"
 native="false"
 synchronized="false"
 static="false"
 final="false"
 deprecated="not deprecated"
 visibility="public"
>
</method>
<method name="getScheme"
 return="java.lang.String"
 abstract="false"
 native="false"
 synchronized="false"
 static="false"
 final="false"
 deprecated="not deprecated"
 visibility="public"
>
</method>
<method name="getUri"
 return="java.lang.String"
 abstract="false"
 native="false"
 synchronized="false"
 static="false"
 final="false"
 deprecated="not deprecated"
 visibility="public"
>
</method>
<method name="getVerb"
 return="java.lang.String"
 abstract="false"
 native="false"
 synchronized="false"
 static="false"
 final="false"
 deprecated="not deprecated"
 visibility="public"
>
</method>
<method name="isSsl"
 return="boolean"
 abstract="false"
 native="false"
 synchronized="false"
 static="false"
 final="false"
 deprecated="not deprecated"
 visibility="public"
>
</method>
</class>
<class name="Response"
 extends="java.lang.Object"
 abstract="false"
 static="false"
 final="false"
 deprecated="not deprecated"
 visibility="public"
>
<method name="getBody"
 return="java.lang.String"
 abstract="false"
 native="false"
 synchronized="false"
 static="false"
 final="false"
 deprecated="not deprecated"
 visibility="public"
>
</method>
<method name="getData"
 return="com.google.gson.JsonElement"
 abstract="false"
 native="false"
 synchronized="false"
 static="false"
 final="false"
 deprecated="not deprecated"
 visibility="public"
>
</method>
<method name="getRequest"
 return="com.amadeus.Request"
 abstract="false"
 native="false"
 synchronized="false"
 static="false"
 final="false"
 deprecated="not deprecated"
 visibility="public"
>
</method>
<method name="getResult"
 return="com.google.gson.JsonObject"
 abstract="false"
 native="false"
 synchronized="false"
 static="false"
 final="false"
 deprecated="not deprecated"
 visibility="public"
>
</method>
<method name="getStatusCode"
 return="int"
 abstract="false"
 native="false"
 synchronized="false"
 static="false"
 final="false"
 deprecated="not deprecated"
 visibility="public"
>
</method>
<method name="isParsed"
 return="boolean"
 abstract="false"
 native="false"
 synchronized="false"
 static="false"
 final="false"
 deprecated="not deprecated"
 visibility="public"
>
</method>
</class>
<class name="Shopping"
 extends="java.lang.Object"
 abstract="false"
 static="false"
 final="false"
 deprecated="not deprecated"
 visibility="public"
>
<method name="hotel"
 return="com.amadeus.shopping.Hotel"
 abstract="false"
 native="false"
 synchronized="false"
 static="false"
 final="false"
 deprecated="not deprecated"
 visibility="public"
>
<parameter name="hotelId" type="java.lang.String">
</parameter>
</method>
<field name="flightDates"
 type="com.amadeus.shopping.FlightDates"
 transient="false"
 volatile="false"
 static="false"
 final="false"
 deprecated="not deprecated"
 visibility="public"
>
</field>
<field name="flightDestinations"
 type="com.amadeus.shopping.FlightDestinations"
 transient="false"
 volatile="false"
 static="false"
 final="false"
 deprecated="not deprecated"
 visibility="public"
>
</field>
<field name="flightOffers"
 type="com.amadeus.shopping.FlightOffers"
 transient="false"
 volatile="false"
 static="false"
 final="false"
 deprecated="not deprecated"
 visibility="public"
>
</field>
<field name="hotelOffers"
 type="com.amadeus.shopping.HotelOffers"
 transient="false"
 volatile="false"
 static="false"
 final="false"
 deprecated="not deprecated"
 visibility="public"
>
</field>
</class>
<class name="Travel"
 extends="java.lang.Object"
 abstract="false"
 static="false"
 final="false"
 deprecated="not deprecated"
 visibility="public"
>
<field name="analytics"
 type="com.amadeus.travel.analytics.Analytics"
 transient="false"
 volatile="false"
 static="false"
 final="false"
 deprecated="not deprecated"
 visibility="public"
>
</field>
</class>
</package>
<package name="com.amadeus.exceptions"
>
<class name="AuthenticationException"
 extends="com.amadeus.exceptions.ResponseException"
 abstract="false"
 static="false"
 final="false"
 deprecated="not deprecated"
 visibility="public"
>
</class>
<class name="ClientException"
 extends="com.amadeus.exceptions.ResponseException"
 abstract="false"
 static="false"
 final="false"
 deprecated="not deprecated"
 visibility="public"
>
</class>
<class name="NetworkException"
 extends="com.amadeus.exceptions.ResponseException"
 abstract="false"
 static="false"
 final="false"
 deprecated="not deprecated"
 visibility="public"
>
</class>
<class name="NotFoundException"
 extends="com.amadeus.exceptions.ResponseException"
 abstract="false"
 static="false"
 final="false"
 deprecated="not deprecated"
 visibility="public"
>
<constructor name="NotFoundException"
 type="com.amadeus.exceptions.NotFoundException"
 static="false"
 final="false"
 deprecated="not deprecated"
 visibility="public"
>
<parameter name="response" type="com.amadeus.Response">
</parameter>
</constructor>
</class>
<class name="ParserException"
 extends="com.amadeus.exceptions.ResponseException"
 abstract="false"
 static="false"
 final="false"
 deprecated="not deprecated"
 visibility="public"
>
</class>
<class name="ResponseException"
 extends="java.lang.Exception"
 abstract="false"
 static="false"
 final="false"
 deprecated="not deprecated"
 visibility="public"
>
<method name="getCode"
 return="java.lang.String"
 abstract="false"
 native="false"
 synchronized="false"
 static="false"
 final="false"
 deprecated="not deprecated"
 visibility="public"
>
</method>
<method name="getDescription"
 return="java.lang.String"
 abstract="false"
 native="false"
 synchronized="false"
 static="false"
 final="false"
 deprecated="not deprecated"
 visibility="public"
>
</method>
<method name="getResponse"
 return="com.amadeus.Response"
 abstract="false"
 native="false"
 synchronized="false"
 static="false"
 final="false"
 deprecated="not deprecated"
 visibility="public"
>
</method>
</class>
<class name="ServerException"
 extends="com.amadeus.exceptions.ResponseException"
 abstract="false"
 static="false"
 final="false"
 deprecated="not deprecated"
 visibility="public"
>
</class>
</package>
<package name="com.amadeus.referenceData"
>
<class name="Airlines"
 extends="java.lang.Object"
 abstract="false"
 static="false"
 final="false"
 deprecated="not deprecated"
 visibility="public"
>
<method name="get"
 return="com.amadeus.resources.Airline[]"
 abstract="false"
 native="false"
 synchronized="false"
 static="false"
 final="false"
 deprecated="not deprecated"
 visibility="public"
>
<parameter name="params" type="com.amadeus.Params">
</parameter>
<exception name="ResponseException" type="com.amadeus.exceptions.ResponseException">
</exception>
</method>
<method name="get"
 return="com.amadeus.resources.Airline[]"
 abstract="false"
 native="false"
 synchronized="false"
 static="false"
 final="false"
 deprecated="not deprecated"
 visibility="public"
>
<exception name="ResponseException" type="com.amadeus.exceptions.ResponseException">
</exception>
</method>
</class>
<class name="Location"
 extends="java.lang.Object"
 abstract="false"
 static="false"
 final="false"
 deprecated="not deprecated"
 visibility="public"
>
<method name="get"
 return="com.amadeus.resources.Location"
 abstract="false"
 native="false"
 synchronized="false"
 static="false"
 final="false"
 deprecated="not deprecated"
 visibility="public"
>
<parameter name="params" type="com.amadeus.Params">
</parameter>
<exception name="ResponseException" type="com.amadeus.exceptions.ResponseException">
</exception>
</method>
<method name="get"
 return="com.amadeus.resources.Location"
 abstract="false"
 native="false"
 synchronized="false"
 static="false"
 final="false"
 deprecated="not deprecated"
 visibility="public"
>
<exception name="ResponseException" type="com.amadeus.exceptions.ResponseException">
</exception>
</method>
</class>
<class name="Locations"
 extends="java.lang.Object"
 abstract="false"
 static="false"
 final="false"
 deprecated="not deprecated"
 visibility="public"
>
<method name="get"
 return="com.amadeus.resources.Location[]"
 abstract="false"
 native="false"
 synchronized="false"
 static="false"
 final="false"
 deprecated="not deprecated"
 visibility="public"
>
<parameter name="params" type="com.amadeus.Params">
</parameter>
<exception name="ResponseException" type="com.amadeus.exceptions.ResponseException">
</exception>
</method>
<method name="get"
 return="com.amadeus.resources.Location[]"
 abstract="false"
 native="false"
 synchronized="false"
 static="false"
 final="false"
 deprecated="not deprecated"
 visibility="public"
>
<exception name="ResponseException" type="com.amadeus.exceptions.ResponseException">
</exception>
</method>
<field name="AIRPORT"
 type="java.lang.String"
 transient="false"
 volatile="false"
 static="true"
 final="false"
 deprecated="not deprecated"
 visibility="public"
>
</field>
<field name="ANY"
 type="java.lang.String"
 transient="false"
 volatile="false"
 static="true"
 final="false"
 deprecated="not deprecated"
 visibility="public"
>
</field>
<field name="CITY"
 type="java.lang.String"
 transient="false"
 volatile="false"
 static="true"
 final="false"
 deprecated="not deprecated"
 visibility="public"
>
</field>
<field name="airports"
 type="com.amadeus.referenceData.locations.Airports"
 transient="false"
 volatile="false"
 static="false"
 final="false"
 deprecated="not deprecated"
 visibility="public"
>
</field>
</class>
<class name="Urls"
 extends="java.lang.Object"
 abstract="false"
 static="false"
 final="false"
 deprecated="not deprecated"
 visibility="public"
>
<field name="checkinLinks"
 type="com.amadeus.referenceData.urls.CheckinLinks"
 transient="false"
 volatile="false"
 static="false"
 final="false"
 deprecated="not deprecated"
 visibility="public"
>
</field>
</class>
</package>
<package name="com.amadeus.referenceData.locations"
>
<class name="Airports"
 extends="java.lang.Object"
 abstract="false"
 static="false"
 final="false"
 deprecated="not deprecated"
 visibility="public"
>
<method name="get"
 return="com.amadeus.resources.Location[]"
 abstract="false"
 native="false"
 synchronized="false"
 static="false"
 final="false"
 deprecated="not deprecated"
 visibility="public"
>
<parameter name="params" type="com.amadeus.Params">
</parameter>
<exception name="ResponseException" type="com.amadeus.exceptions.ResponseException">
</exception>
</method>
<method name="get"
 return="com.amadeus.resources.Location[]"
 abstract="false"
 native="false"
 synchronized="false"
 static="false"
 final="false"
 deprecated="not deprecated"
 visibility="public"
>
<exception name="ResponseException" type="com.amadeus.exceptions.ResponseException">
</exception>
</method>
</class>
</package>
<package name="com.amadeus.referenceData.urls"
>
<class name="CheckinLinks"
 extends="java.lang.Object"
 abstract="false"
 static="false"
 final="false"
 deprecated="not deprecated"
 visibility="public"
>
<method name="get"
 return="com.amadeus.resources.CheckinLink[]"
 abstract="false"
 native="false"
 synchronized="false"
 static="false"
 final="false"
 deprecated="not deprecated"
 visibility="public"
>
<parameter name="params" type="com.amadeus.Params">
</parameter>
<exception name="ResponseException" type="com.amadeus.exceptions.ResponseException">
</exception>
</method>
<method name="get"
 return="com.amadeus.resources.CheckinLink[]"
 abstract="false"
 native="false"
 synchronized="false"
 static="false"
 final="false"
 deprecated="not deprecated"
 visibility="public"
>
<exception name="ResponseException" type="com.amadeus.exceptions.ResponseException">
</exception>
</method>
</class>
</package>
<package name="com.amadeus.resources"
>
<class name="AirTraffic"
 extends="com.amadeus.resources.Resource"
 abstract="false"
 static="false"
 final="false"
 deprecated="not deprecated"
 visibility="public"
>
<method name="getAnalytics"
 return="com.amadeus.resources.AirTraffic.Analytics"
 abstract="false"
 native="false"
 synchronized="false"
 static="false"
 final="false"
 deprecated="not deprecated"
 visibility="public"
>
</method>
<method name="getDestination"
 return="java.lang.String"
 abstract="false"
 native="false"
 synchronized="false"
 static="false"
 final="false"
 deprecated="not deprecated"
 visibility="public"
>
</method>
<method name="getSubType"
 return="java.lang.String"
 abstract="false"
 native="false"
 synchronized="false"
 static="false"
 final="false"
 deprecated="not deprecated"
 visibility="public"
>
</method>
<method name="getType"
 return="java.lang.String"
 abstract="false"
 native="false"
 synchronized="false"
 static="false"
 final="false"
 deprecated="not deprecated"
 visibility="public"
>
</method>
</class>
<class name="AirTraffic.Analytics"
 extends="java.lang.Object"
 abstract="false"
 static="false"
 final="false"
 deprecated="not deprecated"
 visibility="public"
>
<method name="getFlights"
 return="com.amadeus.resources.AirTraffic.Analytics.Flights"
 abstract="false"
 native="false"
 synchronized="false"
 static="false"
 final="false"
 deprecated="not deprecated"
 visibility="public"
>
</method>
<method name="getTravelers"
 return="com.amadeus.resources.AirTraffic.Analytics.Travelers"
 abstract="false"
 native="false"
 synchronized="false"
 static="false"
 final="false"
 deprecated="not deprecated"
 visibility="public"
>
</method>
</class>
<class name="AirTraffic.Analytics.Flights"
 extends="java.lang.Object"
 abstract="false"
 static="false"
 final="false"
 deprecated="not deprecated"
 visibility="public"
>
<method name="getScore"
 return="java.lang.Double"
 abstract="false"
 native="false"
 synchronized="false"
 static="false"
 final="false"
 deprecated="not deprecated"
 visibility="public"
>
</method>
</class>
<class name="AirTraffic.Analytics.Travelers"
 extends="java.lang.Object"
 abstract="false"
 static="false"
 final="false"
 deprecated="not deprecated"
 visibility="public"
>
<method name="getScore"
 return="java.lang.Double"
 abstract="false"
 native="false"
 synchronized="false"
 static="false"
 final="false"
 deprecated="not deprecated"
 visibility="public"
>
</method>
</class>
<class name="Airline"
 extends="com.amadeus.resources.Resource"
 abstract="false"
 static="false"
 final="false"
 deprecated="not deprecated"
 visibility="public"
>
<method name="getBusinessName"
 return="java.lang.String"
 abstract="false"
 native="false"
 synchronized="false"
 static="false"
 final="false"
 deprecated="not deprecated"
 visibility="public"
>
</method>
<method name="getCommonName"
 return="java.lang.String"
 abstract="false"
 native="false"
 synchronized="false"
 static="false"
 final="false"
 deprecated="not deprecated"
 visibility="public"
>
</method>
<method name="getIataCode"
 return="java.lang.String"
 abstract="false"
 native="false"
 synchronized="false"
 static="false"
 final="false"
 deprecated="not deprecated"
 visibility="public"
>
</method>
<method name="getIcaoCode"
 return="java.lang.String"
 abstract="false"
 native="false"
 synchronized="false"
 static="false"
 final="false"
 deprecated="not deprecated"
 visibility="public"
>
</method>
<method name="getType"
 return="java.lang.String"
 abstract="false"
 native="false"
 synchronized="false"
 static="false"
 final="false"
 deprecated="not deprecated"
 visibility="public"
>
</method>
</class>
<class name="CheckinLink"
 extends="com.amadeus.resources.Resource"
 abstract="false"
 static="false"
 final="false"
 deprecated="not deprecated"
 visibility="public"
>
<method name="getChannel"
 return="java.lang.String"
 abstract="false"
 native="false"
 synchronized="false"
 static="false"
 final="false"
 deprecated="not deprecated"
 visibility="public"
>
</method>
<method name="getHref"
 return="java.lang.String"
 abstract="false"
 native="false"
 synchronized="false"
 static="false"
 final="false"
 deprecated="not deprecated"
 visibility="public"
>
</method>
<method name="getId"
 return="java.lang.String"
 abstract="false"
 native="false"
 synchronized="false"
 static="false"
 final="false"
 deprecated="not deprecated"
 visibility="public"
>
</method>
<method name="getType"
 return="java.lang.String"
 abstract="false"
 native="false"
 synchronized="false"
 static="false"
 final="false"
 deprecated="not deprecated"
 visibility="public"
>
</method>
</class>
<class name="FareSearch"
 extends="com.amadeus.resources.Resource"
 abstract="false"
 static="false"
 final="false"
 deprecated="not deprecated"
 visibility="public"
>
<method name="getNumberOfSearches"
 return="com.amadeus.resources.FareSearch.NumberOfSearches"
 abstract="false"
 native="false"
 synchronized="false"
 static="false"
 final="false"
 deprecated="not deprecated"
 visibility="public"
>
</method>
<method name="getOrigin"
 return="java.lang.String"
 abstract="false"
 native="false"
 synchronized="false"
 static="false"
 final="false"
 deprecated="not deprecated"
 visibility="public"
>
</method>
<method name="getPeriod"
 return="java.lang.String"
 abstract="false"
 native="false"
 synchronized="false"
 static="false"
 final="false"
 deprecated="not deprecated"
 visibility="public"
>
</method>
<method name="getSourceCountry"
 return="java.lang.String"
 abstract="false"
 native="false"
 synchronized="false"
 static="false"
 final="false"
 deprecated="not deprecated"
 visibility="public"
>
</method>
<method name="getType"
 return="java.lang.String"
 abstract="false"
 native="false"
 synchronized="false"
 static="false"
 final="false"
 deprecated="not deprecated"
 visibility="public"
>
</method>
</class>
<class name="FareSearch.NumberOfSearches"
 extends="java.lang.Object"
 abstract="false"
 static="false"
 final="false"
 deprecated="not deprecated"
 visibility="public"
>
<method name="getPerDaysInAdvance"
 return="java.util.HashMap&lt;java.lang.String, java.lang.Integer&gt;"
 abstract="false"
 native="false"
 synchronized="false"
 static="false"
 final="false"
 deprecated="not deprecated"
 visibility="public"
>
</method>
<method name="getPerDestination"
 return="java.util.HashMap&lt;java.lang.String, java.lang.String&gt;"
 abstract="false"
 native="false"
 synchronized="false"
 static="false"
 final="false"
 deprecated="not deprecated"
 visibility="public"
>
</method>
<method name="getPerTripDuration"
 return="java.util.HashMap&lt;java.lang.String, java.lang.Integer&gt;"
 abstract="false"
 native="false"
 synchronized="false"
 static="false"
 final="false"
 deprecated="not deprecated"
 visibility="public"
>
</method>
</class>
<class name="FlightDate"
 extends="com.amadeus.resources.Resource"
 abstract="false"
 static="false"
 final="false"
 deprecated="not deprecated"
 visibility="public"
>
<method name="getDepartureDate"
 return="java.util.Date"
 abstract="false"
 native="false"
 synchronized="false"
 static="false"
 final="false"
 deprecated="not deprecated"
 visibility="public"
>
</method>
<method name="getDestination"
 return="java.lang.String"
 abstract="false"
 native="false"
 synchronized="false"
 static="false"
 final="false"
 deprecated="not deprecated"
 visibility="public"
>
</method>
<method name="getOrigin"
 return="java.lang.String"
 abstract="false"
 native="false"
 synchronized="false"
 static="false"
 final="false"
 deprecated="not deprecated"
 visibility="public"
>
</method>
<method name="getPrice"
 return="com.amadeus.resources.FlightDate.Price"
 abstract="false"
 native="false"
 synchronized="false"
 static="false"
 final="false"
 deprecated="not deprecated"
 visibility="public"
>
</method>
<method name="getReturnDate"
 return="java.util.Date"
 abstract="false"
 native="false"
 synchronized="false"
 static="false"
 final="false"
 deprecated="not deprecated"
 visibility="public"
>
</method>
<method name="getType"
 return="java.lang.String"
 abstract="false"
 native="false"
 synchronized="false"
 static="false"
 final="false"
 deprecated="not deprecated"
 visibility="public"
>
</method>
</class>
<class name="FlightDate.Price"
 extends="java.lang.Object"
 abstract="false"
 static="false"
 final="false"
 deprecated="not deprecated"
 visibility="public"
>
<method name="getTotal"
 return="double"
 abstract="false"
 native="false"
 synchronized="false"
 static="false"
 final="false"
 deprecated="not deprecated"
 visibility="public"
>
</method>
</class>
<class name="FlightDestination"
 extends="com.amadeus.resources.Resource"
 abstract="false"
 static="false"
 final="false"
 deprecated="not deprecated"
 visibility="public"
>
<method name="getDepartureDate"
 return="java.util.Date"
 abstract="false"
 native="false"
 synchronized="false"
 static="false"
 final="false"
 deprecated="not deprecated"
 visibility="public"
>
</method>
<method name="getDestination"
 return="java.lang.String"
 abstract="false"
 native="false"
 synchronized="false"
 static="false"
 final="false"
 deprecated="not deprecated"
 visibility="public"
>
</method>
<method name="getOrigin"
 return="java.lang.String"
 abstract="false"
 native="false"
 synchronized="false"
 static="false"
 final="false"
 deprecated="not deprecated"
 visibility="public"
>
</method>
<method name="getPrice"
 return="com.amadeus.resources.FlightDestination.Price"
 abstract="false"
 native="false"
 synchronized="false"
 static="false"
 final="false"
 deprecated="not deprecated"
 visibility="public"
>
</method>
<method name="getReturnDate"
 return="java.util.Date"
 abstract="false"
 native="false"
 synchronized="false"
 static="false"
 final="false"
 deprecated="not deprecated"
 visibility="public"
>
</method>
<method name="getType"
 return="java.lang.String"
 abstract="false"
 native="false"
 synchronized="false"
 static="false"
 final="false"
 deprecated="not deprecated"
 visibility="public"
>
</method>
</class>
<class name="FlightDestination.Price"
 extends="java.lang.Object"
 abstract="false"
 static="false"
 final="false"
 deprecated="not deprecated"
 visibility="public"
>
<method name="getTotal"
 return="double"
 abstract="false"
 native="false"
 synchronized="false"
 static="false"
 final="false"
 deprecated="not deprecated"
 visibility="public"
>
</method>
</class>
<class name="FlightOffer"
 extends="com.amadeus.resources.Resource"
 abstract="false"
 static="false"
 final="false"
 deprecated="not deprecated"
 visibility="public"
>
<method name="getId"
 return="java.lang.String"
 abstract="false"
 native="false"
 synchronized="false"
 static="false"
 final="false"
 deprecated="not deprecated"
 visibility="public"
>
</method>
<method name="getOfferItems"
 return="com.amadeus.resources.FlightOffer.OfferItem[]"
 abstract="false"
 native="false"
 synchronized="false"
 static="false"
 final="false"
 deprecated="not deprecated"
 visibility="public"
>
</method>
<method name="getType"
 return="java.lang.String"
 abstract="false"
 native="false"
 synchronized="false"
 static="false"
 final="false"
 deprecated="not deprecated"
 visibility="public"
>
</method>
</class>
<class name="FlightOffer.AircraftEquipment"
 extends="java.lang.Object"
 abstract="false"
 static="false"
 final="false"
 deprecated="not deprecated"
 visibility="public"
>
<method name="getCode"
 return="java.lang.String"
 abstract="false"
 native="false"
 synchronized="false"
 static="false"
 final="false"
 deprecated="not deprecated"
 visibility="public"
>
</method>
</class>
<class name="FlightOffer.FlightEndPoint"
 extends="java.lang.Object"
 abstract="false"
 static="false"
 final="false"
 deprecated="not deprecated"
 visibility="public"
>
<method name="getAt"
 return="java.lang.String"
 abstract="false"
 native="false"
 synchronized="false"
 static="false"
 final="false"
 deprecated="not deprecated"
 visibility="public"
>
</method>
<method name="getIataCode"
 return="java.lang.String"
 abstract="false"
 native="false"
 synchronized="false"
 static="false"
 final="false"
 deprecated="not deprecated"
 visibility="public"
>
</method>
<method name="getTerminal"
 return="java.lang.String"
 abstract="false"
 native="false"
 synchronized="false"
 static="false"
 final="false"
 deprecated="not deprecated"
 visibility="public"
>
</method>
</class>
<class name="FlightOffer.FlightSegment"
 extends="java.lang.Object"
 abstract="false"
 static="false"
 final="false"
 deprecated="not deprecated"
 visibility="public"
>
<method name="getArrival"
 return="com.amadeus.resources.FlightOffer.FlightEndPoint"
 abstract="false"
 native="false"
 synchronized="false"
 static="false"
 final="false"
 deprecated="not deprecated"
 visibility="public"
>
</method>
<method name="getCarrierCode"
 return="java.lang.String"
 abstract="false"
 native="false"
 synchronized="false"
 static="false"
 final="false"
 deprecated="not deprecated"
 visibility="public"
>
</method>
<method name="getDeparture"
 return="com.amadeus.resources.FlightOffer.FlightEndPoint"
 abstract="false"
 native="false"
 synchronized="false"
 static="false"
 final="false"
 deprecated="not deprecated"
 visibility="public"
>
</method>
<method name="getDuration"
 return="java.lang.String"
 abstract="false"
 native="false"
 synchronized="false"
 static="false"
 final="false"
 deprecated="not deprecated"
 visibility="public"
>
</method>
<method name="getNumber"
 return="java.lang.String"
 abstract="false"
 native="false"
 synchronized="false"
 static="false"
 final="false"
 deprecated="not deprecated"
 visibility="public"
>
</method>
<method name="getOperating"
 return="com.amadeus.resources.FlightOffer.OperatingFlight"
 abstract="false"
 native="false"
 synchronized="false"
 static="false"
 final="false"
 deprecated="not deprecated"
 visibility="public"
>
</method>
<method name="getStops"
 return="com.amadeus.resources.FlightOffer.FlightStop[]"
 abstract="false"
 native="false"
 synchronized="false"
 static="false"
 final="false"
 deprecated="not deprecated"
 visibility="public"
>
</method>
</class>
<class name="FlightOffer.FlightStop"
 extends="java.lang.Object"
 abstract="false"
 static="false"
 final="false"
 deprecated="not deprecated"
 visibility="public"
>
<method name="getArrivalAt"
 return="java.util.Date"
 abstract="false"
 native="false"
 synchronized="false"
 static="false"
 final="false"
 deprecated="not deprecated"
 visibility="public"
>
</method>
<method name="getDepartureAt"
 return="java.util.Date"
 abstract="false"
 native="false"
 synchronized="false"
 static="false"
 final="false"
 deprecated="not deprecated"
 visibility="public"
>
</method>
<method name="getDuration"
 return="java.lang.String"
 abstract="false"
 native="false"
 synchronized="false"
 static="false"
 final="false"
 deprecated="not deprecated"
 visibility="public"
>
</method>
<method name="getIataCode"
 return="java.lang.String"
 abstract="false"
 native="false"
 synchronized="false"
 static="false"
 final="false"
 deprecated="not deprecated"
 visibility="public"
>
</method>
<method name="getNewAircraft"
 return="com.amadeus.resources.FlightOffer.AircraftEquipment"
 abstract="false"
 native="false"
 synchronized="false"
 static="false"
 final="false"
 deprecated="not deprecated"
 visibility="public"
>
</method>
</class>
<class name="FlightOffer.OfferItem"
 extends="java.lang.Object"
 abstract="false"
 static="false"
 final="false"
 deprecated="not deprecated"
 visibility="public"
>
<method name="getPrice"
 return="com.amadeus.resources.FlightOffer.Price"
 abstract="false"
 native="false"
 synchronized="false"
 static="false"
 final="false"
 deprecated="not deprecated"
 visibility="public"
>
</method>
<method name="getPricePerAdult"
 return="com.amadeus.resources.FlightOffer.Price"
 abstract="false"
 native="false"
 synchronized="false"
 static="false"
 final="false"
 deprecated="not deprecated"
 visibility="public"
>
</method>
<method name="getPricePerChild"
 return="com.amadeus.resources.FlightOffer.Price"
 abstract="false"
 native="false"
 synchronized="false"
 static="false"
 final="false"
 deprecated="not deprecated"
 visibility="public"
>
</method>
<method name="getPricePerInfant"
 return="com.amadeus.resources.FlightOffer.Price"
 abstract="false"
 native="false"
 synchronized="false"
 static="false"
 final="false"
 deprecated="not deprecated"
 visibility="public"
>
</method>
<method name="getPricePerSenior"
 return="com.amadeus.resources.FlightOffer.Price"
 abstract="false"
 native="false"
 synchronized="false"
 static="false"
 final="false"
 deprecated="not deprecated"
 visibility="public"
>
</method>
<method name="getServices"
 return="com.amadeus.resources.FlightOffer.Service[]"
 abstract="false"
 native="false"
 synchronized="false"
 static="false"
 final="false"
 deprecated="not deprecated"
 visibility="public"
>
</method>
</class>
<class name="FlightOffer.OperatingFlight"
 extends="java.lang.Object"
 abstract="false"
 static="false"
 final="false"
 deprecated="not deprecated"
 visibility="public"
>
<method name="getCarrierCode"
 return="java.lang.String"
 abstract="false"
 native="false"
 synchronized="false"
 static="false"
 final="false"
 deprecated="not deprecated"
 visibility="public"
>
</method>
<method name="getNumber"
 return="java.lang.String"
 abstract="false"
 native="false"
 synchronized="false"
 static="false"
 final="false"
 deprecated="not deprecated"
 visibility="public"
>
</method>
</class>
<class name="FlightOffer.Price"
 extends="java.lang.Object"
 abstract="false"
 static="false"
 final="false"
 deprecated="not deprecated"
 visibility="public"
>
<method name="getTotal"
 return="double"
 abstract="false"
 native="false"
 synchronized="false"
 static="false"
 final="false"
 deprecated="not deprecated"
 visibility="public"
>
</method>
<method name="getTotalTaxes"
 return="double"
 abstract="false"
 native="false"
 synchronized="false"
 static="false"
 final="false"
 deprecated="not deprecated"
 visibility="public"
>
</method>
</class>
<class name="FlightOffer.PricingDetail"
 extends="java.lang.Object"
 abstract="false"
 static="false"
 final="false"
 deprecated="not deprecated"
 visibility="public"
>
<method name="getAvailability"
 return="int"
 abstract="false"
 native="false"
 synchronized="false"
 static="false"
 final="false"
 deprecated="not deprecated"
 visibility="public"
>
</method>
<method name="getFareBasis"
 return="java.lang.String"
 abstract="false"
 native="false"
 synchronized="false"
 static="false"
 final="false"
 deprecated="not deprecated"
 visibility="public"
>
</method>
<method name="getFareClass"
 return="java.lang.String"
 abstract="false"
 native="false"
 synchronized="false"
 static="false"
 final="false"
 deprecated="not deprecated"
 visibility="public"
>
</method>
<method name="getTravelClass"
 return="java.lang.String"
 abstract="false"
 native="false"
 synchronized="false"
 static="false"
 final="false"
 deprecated="not deprecated"
 visibility="public"
>
</method>
</class>
<class name="FlightOffer.Segment"
 extends="java.lang.Object"
 abstract="false"
 static="false"
 final="false"
 deprecated="not deprecated"
 visibility="public"
>
<method name="getFlightSegment"
 return="com.amadeus.resources.FlightOffer.FlightSegment"
 abstract="false"
 native="false"
 synchronized="false"
 static="false"
 final="false"
 deprecated="not deprecated"
 visibility="public"
>
</method>
<method name="getPricingDetailPerAdult"
 return="com.amadeus.resources.FlightOffer.PricingDetail"
 abstract="false"
 native="false"
 synchronized="false"
 static="false"
 final="false"
 deprecated="not deprecated"
 visibility="public"
>
</method>
<method name="getPricingDetailPerChild"
 return="com.amadeus.resources.FlightOffer.PricingDetail"
 abstract="false"
 native="false"
 synchronized="false"
 static="false"
 final="false"
 deprecated="not deprecated"
 visibility="public"
>
</method>
<method name="getPricingDetailPerInfant"
 return="com.amadeus.resources.FlightOffer.PricingDetail"
 abstract="false"
 native="false"
 synchronized="false"
 static="false"
 final="false"
 deprecated="not deprecated"
 visibility="public"
>
</method>
<method name="getPricingDetailPerSenior"
 return="com.amadeus.resources.FlightOffer.PricingDetail"
 abstract="false"
 native="false"
 synchronized="false"
 static="false"
 final="false"
 deprecated="not deprecated"
 visibility="public"
>
</method>
</class>
<class name="FlightOffer.Service"
 extends="java.lang.Object"
 abstract="false"
 static="false"
 final="false"
 deprecated="not deprecated"
 visibility="public"
>
<method name="getSegments"
 return="com.amadeus.resources.FlightOffer.Segment[]"
 abstract="false"
 native="false"
 synchronized="false"
 static="false"
 final="false"
 deprecated="not deprecated"
 visibility="public"
>
</method>
</class>
<class name="HotelOffer"
 extends="com.amadeus.resources.Resource"
 abstract="false"
 static="false"
 final="false"
 deprecated="not deprecated"
 visibility="public"
>
<method name="getHotel"
 return="com.amadeus.resources.HotelOffer.Hotel"
 abstract="false"
 native="false"
 synchronized="false"
 static="false"
 final="false"
 deprecated="not deprecated"
 visibility="public"
>
</method>
<method name="getOffers"
 return="com.amadeus.resources.HotelOffer.Offer[]"
 abstract="false"
 native="false"
 synchronized="false"
 static="false"
 final="false"
 deprecated="not deprecated"
 visibility="public"
>
</method>
<method name="getType"
 return="java.lang.String"
 abstract="false"
 native="false"
 synchronized="false"
 static="false"
 final="false"
 deprecated="not deprecated"
 visibility="public"
>
</method>
<method name="isAvailable"
 return="boolean"
 abstract="false"
 native="false"
 synchronized="false"
 static="false"
 final="false"
 deprecated="not deprecated"
 visibility="public"
>
</method>
</class>
<class name="HotelOffer.Offer"
 extends="com.amadeus.resources.Resource"
 abstract="false"
 static="false"
 final="false"
 deprecated="not deprecated"
 visibility="public"
>
<method name="getBoardType"
 return="java.lang.String"
 abstract="false"
 native="false"
 synchronized="false"
 static="false"
 final="false"
 deprecated="not deprecated"
 visibility="public"
>
</method>
<method name="getBookingCode"
 return="java.lang.String"
 abstract="false"
 native="false"
 synchronized="false"
 static="false"
 final="false"
 deprecated="not deprecated"
 visibility="public"
>
</method>
<method name="getCategory"
 return="java.lang.String"
 abstract="false"
 native="false"
 synchronized="false"
 static="false"
 final="false"
 deprecated="not deprecated"
 visibility="public"
>
</method>
<method name="getCommission"
 return="com.amadeus.resources.HotelOffer.Commission"
 abstract="false"
 native="false"
 synchronized="false"
 static="false"
 final="false"
 deprecated="not deprecated"
 visibility="public"
>
</method>
<method name="getDescription"
 return="com.amadeus.resources.HotelOffer.TextWithLanguageType"
 abstract="false"
 native="false"
 synchronized="false"
 static="false"
 final="false"
 deprecated="not deprecated"
 visibility="public"
>
</method>
<method name="getGuests"
 return="com.amadeus.resources.HotelOffer.Guests"
 abstract="false"
 native="false"
 synchronized="false"
 static="false"
 final="false"
 deprecated="not deprecated"
 visibility="public"
>
</method>
<method name="getId"
 return="java.lang.String"
 abstract="false"
 native="false"
 synchronized="false"
 static="false"
 final="false"
 deprecated="not deprecated"
 visibility="public"
>
</method>
<method name="getPolicies"
 return="com.amadeus.resources.HotelOffer.PolicyDetails"
 abstract="false"
 native="false"
 synchronized="false"
 static="false"
 final="false"
 deprecated="not deprecated"
 visibility="public"
>
</method>
<method name="getPrice"
 return="com.amadeus.resources.HotelOffer.HotelPrice"
 abstract="false"
 native="false"
 synchronized="false"
 static="false"
 final="false"
 deprecated="not deprecated"
 visibility="public"
>
</method>
<method name="getRateCode"
 return="java.lang.String"
 abstract="false"
 native="false"
 synchronized="false"
 static="false"
 final="false"
 deprecated="not deprecated"
 visibility="public"
>
</method>
<method name="getRateFamilyEstimated"
 return="com.amadeus.resources.HotelOffer.RateFamily"
 abstract="false"
 native="false"
 synchronized="false"
 static="false"
 final="false"
 deprecated="not deprecated"
 visibility="public"
>
</method>
<method name="getRoom"
 return="com.amadeus.resources.HotelOffer.RoomDetails"
 abstract="false"
 native="false"
 synchronized="false"
 static="false"
 final="false"
 deprecated="not deprecated"
 visibility="public"
>
</method>
<method name="getRoomQuantity"
 return="java.lang.Integer"
 abstract="false"
 native="false"
 synchronized="false"
 static="false"
 final="false"
 deprecated="not deprecated"
 visibility="public"
>
</method>
<method name="getType"
 return="java.lang.String"
 abstract="false"
 native="false"
 synchronized="false"
 static="false"
 final="false"
 deprecated="not deprecated"
 visibility="public"
>
</method>
</class>
<class name="Location"
 extends="com.amadeus.resources.Resource"
 abstract="false"
 static="false"
 final="false"
 deprecated="not deprecated"
 visibility="public"
>
<method name="getAddress"
 return="com.amadeus.resources.Location.Address"
 abstract="false"
 native="false"
 synchronized="false"
 static="false"
 final="false"
 deprecated="not deprecated"
 visibility="public"
>
</method>
<method name="getAnalytics"
 return="com.amadeus.resources.Location.Analytics"
 abstract="false"
 native="false"
 synchronized="false"
 static="false"
 final="false"
 deprecated="not deprecated"
 visibility="public"
>
</method>
<method name="getDetailedName"
 return="java.lang.String"
 abstract="false"
 native="false"
 synchronized="false"
 static="false"
 final="false"
 deprecated="not deprecated"
 visibility="public"
>
</method>
<method name="getDistance"
 return="com.amadeus.resources.Location.Distance"
 abstract="false"
 native="false"
 synchronized="false"
 static="false"
 final="false"
 deprecated="not deprecated"
 visibility="public"
>
</method>
<method name="getGeoCode"
 return="com.amadeus.resources.Location.GeoCode"
 abstract="false"
 native="false"
 synchronized="false"
 static="false"
 final="false"
 deprecated="not deprecated"
 visibility="public"
>
</method>
<method name="getIataCode"
 return="java.lang.String"
 abstract="false"
 native="false"
 synchronized="false"
 static="false"
 final="false"
 deprecated="not deprecated"
 visibility="public"
>
</method>
<method name="getName"
 return="java.lang.String"
 abstract="false"
 native="false"
 synchronized="false"
 static="false"
 final="false"
 deprecated="not deprecated"
 visibility="public"
>
</method>
<method name="getRelevance"
 return="java.lang.Double"
 abstract="false"
 native="false"
 synchronized="false"
 static="false"
 final="false"
 deprecated="not deprecated"
 visibility="public"
>
</method>
<method name="getSubType"
 return="java.lang.String"
 abstract="false"
 native="false"
 synchronized="false"
 static="false"
 final="false"
 deprecated="not deprecated"
 visibility="public"
>
</method>
<method name="getTimeZoneOffset"
 return="java.lang.String"
 abstract="false"
 native="false"
 synchronized="false"
 static="false"
 final="false"
 deprecated="not deprecated"
 visibility="public"
>
</method>
<method name="getType"
 return="java.lang.String"
 abstract="false"
 native="false"
 synchronized="false"
 static="false"
 final="false"
 deprecated="not deprecated"
 visibility="public"
>
</method>
</class>
<class name="Period"
 extends="com.amadeus.resources.Resource"
 abstract="false"
 static="false"
 final="false"
 deprecated="not deprecated"
 visibility="public"
>
<method name="getAnalytics"
 return="com.amadeus.resources.Period.Analytics"
 abstract="false"
 native="false"
 synchronized="false"
 static="false"
 final="false"
 deprecated="not deprecated"
 visibility="public"
>
</method>
<method name="getPeriod"
 return="java.lang.String"
 abstract="false"
 native="false"
 synchronized="false"
 static="false"
 final="false"
 deprecated="not deprecated"
 visibility="public"
>
</method>
<method name="getType"
 return="java.lang.String"
 abstract="false"
 native="false"
 synchronized="false"
 static="false"
 final="false"
 deprecated="not deprecated"
 visibility="public"
>
</method>
</class>
<class name="Period.Analytics"
 extends="java.lang.Object"
 abstract="false"
 static="false"
 final="false"
 deprecated="not deprecated"
 visibility="public"
>
<method name="getTravelers"
 return="com.amadeus.resources.Period.Analytics.Travelers"
 abstract="false"
 native="false"
 synchronized="false"
 static="false"
 final="false"
 deprecated="not deprecated"
 visibility="public"
>
</method>
</class>
<class name="Period.Analytics.Travelers"
 extends="java.lang.Object"
 abstract="false"
 static="false"
 final="false"
 deprecated="not deprecated"
 visibility="public"
>
<method name="getScore"
 return="java.lang.Double"
 abstract="false"
 native="false"
 synchronized="false"
 static="false"
 final="false"
 deprecated="not deprecated"
 visibility="public"
>
</method>
</class>
<class name="Resource"
 extends="java.lang.Object"
 abstract="false"
 static="false"
 final="false"
 deprecated="not deprecated"
 visibility="public"
>
<method name="getResponse"
 return="com.amadeus.Response"
 abstract="false"
 native="false"
 synchronized="false"
 static="false"
 final="false"
 deprecated="not deprecated"
 visibility="public"
>
</method>
</class>
</package>
<package name="com.amadeus.shopping"
>
<class name="FlightDates"
 extends="java.lang.Object"
 abstract="false"
 static="false"
 final="false"
 deprecated="not deprecated"
 visibility="public"
>
<method name="get"
 return="com.amadeus.resources.FlightDate[]"
 abstract="false"
 native="false"
 synchronized="false"
 static="false"
 final="false"
 deprecated="not deprecated"
 visibility="public"
>
<parameter name="params" type="com.amadeus.Params">
</parameter>
<exception name="ResponseException" type="com.amadeus.exceptions.ResponseException">
</exception>
</method>
<method name="get"
 return="com.amadeus.resources.FlightDate[]"
 abstract="false"
 native="false"
 synchronized="false"
 static="false"
 final="false"
 deprecated="not deprecated"
 visibility="public"
>
<exception name="ResponseException" type="com.amadeus.exceptions.ResponseException">
</exception>
</method>
</class>
<class name="FlightDestinations"
 extends="java.lang.Object"
 abstract="false"
 static="false"
 final="false"
 deprecated="not deprecated"
 visibility="public"
>
<method name="get"
 return="com.amadeus.resources.FlightDestination[]"
 abstract="false"
 native="false"
 synchronized="false"
 static="false"
 final="false"
 deprecated="not deprecated"
 visibility="public"
>
<parameter name="params" type="com.amadeus.Params">
</parameter>
<exception name="ResponseException" type="com.amadeus.exceptions.ResponseException">
</exception>
</method>
<method name="get"
 return="com.amadeus.resources.FlightDestination[]"
 abstract="false"
 native="false"
 synchronized="false"
 static="false"
 final="false"
 deprecated="not deprecated"
 visibility="public"
>
<exception name="ResponseException" type="com.amadeus.exceptions.ResponseException">
</exception>
</method>
</class>
<class name="FlightOffers"
 extends="java.lang.Object"
 abstract="false"
 static="false"
 final="false"
 deprecated="not deprecated"
 visibility="public"
>
<method name="get"
 return="com.amadeus.resources.FlightOffer[]"
 abstract="false"
 native="false"
 synchronized="false"
 static="false"
 final="false"
 deprecated="not deprecated"
 visibility="public"
>
<parameter name="params" type="com.amadeus.Params">
</parameter>
<exception name="ResponseException" type="com.amadeus.exceptions.ResponseException">
</exception>
</method>
<method name="get"
 return="com.amadeus.resources.FlightOffer[]"
 abstract="false"
 native="false"
 synchronized="false"
 static="false"
 final="false"
 deprecated="not deprecated"
 visibility="public"
>
<exception name="ResponseException" type="com.amadeus.exceptions.ResponseException">
</exception>
</method>
</class>
<class name="Hotel"
 extends="java.lang.Object"
 abstract="false"
 static="false"
 final="false"
 deprecated="not deprecated"
 visibility="public"
>
<method name="offer"
 return="com.amadeus.shopping.hotel.Offer"
 abstract="false"
 native="false"
 synchronized="false"
 static="false"
 final="false"
 deprecated="not deprecated"
 visibility="public"
>
<parameter name="offerId" type="java.lang.String">
</parameter>
</method>
<field name="hotelOffers"
 type="com.amadeus.shopping.hotel.HotelOffers"
 transient="false"
 volatile="false"
 static="false"
 final="false"
 deprecated="not deprecated"
 visibility="public"
>
</field>
</class>
<class name="HotelOffers"
 extends="java.lang.Object"
 abstract="false"
 static="false"
 final="false"
 deprecated="not deprecated"
 visibility="public"
>
<method name="get"
 return="com.amadeus.resources.HotelOffer[]"
 abstract="false"
 native="false"
 synchronized="false"
 static="false"
 final="false"
 deprecated="not deprecated"
 visibility="public"
>
<parameter name="params" type="com.amadeus.Params">
</parameter>
<exception name="ResponseException" type="com.amadeus.exceptions.ResponseException">
</exception>
</method>
<method name="get"
 return="com.amadeus.resources.HotelOffer[]"
 abstract="false"
 native="false"
 synchronized="false"
 static="false"
 final="false"
 deprecated="not deprecated"
 visibility="public"
>
<exception name="ResponseException" type="com.amadeus.exceptions.ResponseException">
</exception>
</method>
</class>
</package>
<package name="com.amadeus.shopping.hotel"
>
<class name="HotelOffers"
 extends="java.lang.Object"
 abstract="false"
 static="false"
 final="false"
 deprecated="not deprecated"
 visibility="public"
>
<method name="get"
 return="com.amadeus.resources.HotelOffer"
 abstract="false"
 native="false"
 synchronized="false"
 static="false"
 final="false"
 deprecated="not deprecated"
 visibility="public"
>
<parameter name="params" type="com.amadeus.Params">
</parameter>
<exception name="ResponseException" type="com.amadeus.exceptions.ResponseException">
</exception>
</method>
<method name="get"
 return="com.amadeus.resources.HotelOffer"
 abstract="false"
 native="false"
 synchronized="false"
 static="false"
 final="false"
 deprecated="not deprecated"
 visibility="public"
>
<exception name="ResponseException" type="com.amadeus.exceptions.ResponseException">
</exception>
</method>
</class>
<class name="Offer"
 extends="java.lang.Object"
 abstract="false"
 static="false"
 final="false"
 deprecated="not deprecated"
 visibility="public"
>
<method name="get"
 return="com.amadeus.resources.HotelOffer.Offer"
 abstract="false"
 native="false"
 synchronized="false"
 static="false"
 final="false"
 deprecated="not deprecated"
 visibility="public"
>
<parameter name="params" type="com.amadeus.Params">
</parameter>
<exception name="ResponseException" type="com.amadeus.exceptions.ResponseException">
</exception>
</method>
<method name="get"
 return="com.amadeus.resources.HotelOffer.Offer"
 abstract="false"
 native="false"
 synchronized="false"
 static="false"
 final="false"
 deprecated="not deprecated"
 visibility="public"
>
<exception name="ResponseException" type="com.amadeus.exceptions.ResponseException">
</exception>
</method>
</class>
</package>
<package name="com.amadeus.travel.analytics"
>
<class name="AirTraffic"
 extends="java.lang.Object"
 abstract="false"
 static="false"
 final="false"
 deprecated="not deprecated"
 visibility="public"
>
<field name="booked"
 type="com.amadeus.travel.analytics.airTraffic.Booked"
 transient="false"
 volatile="false"
 static="false"
 final="false"
 deprecated="not deprecated"
 visibility="public"
>
</field>
<field name="busiestPeriod"
 type="com.amadeus.travel.analytics.airTraffic.BusiestPeriod"
 transient="false"
 volatile="false"
 static="false"
 final="false"
 deprecated="not deprecated"
 visibility="public"
>
</field>
<field name="traveled"
 type="com.amadeus.travel.analytics.airTraffic.Traveled"
 transient="false"
 volatile="false"
 static="false"
 final="false"
 deprecated="not deprecated"
 visibility="public"
>
</field>
</class>
<class name="Analytics"
 extends="java.lang.Object"
 abstract="false"
 static="false"
 final="false"
 deprecated="not deprecated"
 visibility="public"
>
<field name="airTraffic"
 type="com.amadeus.travel.analytics.AirTraffic"
 transient="false"
 volatile="false"
 static="false"
 final="false"
 deprecated="not deprecated"
 visibility="public"
>
</field>
<field name="fareSearches"
 type="com.amadeus.travel.analytics.FareSearches"
 transient="false"
 volatile="false"
 static="false"
 final="false"
 deprecated="not deprecated"
 visibility="public"
>
</field>
</class>
<class name="FareSearches"
 extends="java.lang.Object"
 abstract="false"
 static="false"
 final="false"
 deprecated="not deprecated"
 visibility="public"
>
<method name="get"
 return="com.amadeus.resources.FareSearch[]"
 abstract="false"
 native="false"
 synchronized="false"
 static="false"
 final="false"
 deprecated="not deprecated"
 visibility="public"
>
<parameter name="params" type="com.amadeus.Params">
</parameter>
<exception name="ResponseException" type="com.amadeus.exceptions.ResponseException">
</exception>
</method>
<method name="get"
 return="com.amadeus.resources.FareSearch[]"
 abstract="false"
 native="false"
 synchronized="false"
 static="false"
 final="false"
 deprecated="not deprecated"
 visibility="public"
>
<exception name="ResponseException" type="com.amadeus.exceptions.ResponseException">
</exception>
</method>
</class>
</package>
<package name="com.amadeus.travel.analytics.airTraffic"
>
<class name="Booked"
 extends="java.lang.Object"
 abstract="false"
 static="false"
 final="false"
 deprecated="not deprecated"
 visibility="public"
>
<method name="get"
 return="com.amadeus.resources.AirTraffic[]"
 abstract="false"
 native="false"
 synchronized="false"
 static="false"
 final="false"
 deprecated="not deprecated"
 visibility="public"
>
<parameter name="params" type="com.amadeus.Params">
</parameter>
<exception name="ResponseException" type="com.amadeus.exceptions.ResponseException">
</exception>
</method>
<method name="get"
 return="com.amadeus.resources.AirTraffic[]"
 abstract="false"
 native="false"
 synchronized="false"
 static="false"
 final="false"
 deprecated="not deprecated"
 visibility="public"
>
<exception name="ResponseException" type="com.amadeus.exceptions.ResponseException">
</exception>
</method>
</class>
<class name="BusiestPeriod"
 extends="java.lang.Object"
 abstract="false"
 static="false"
 final="false"
 deprecated="not deprecated"
 visibility="public"
>
<method name="get"
 return="com.amadeus.resources.Period[]"
 abstract="false"
 native="false"
 synchronized="false"
 static="false"
 final="false"
 deprecated="not deprecated"
 visibility="public"
>
<parameter name="params" type="com.amadeus.Params">
</parameter>
<exception name="ResponseException" type="com.amadeus.exceptions.ResponseException">
</exception>
</method>
<method name="get"
 return="com.amadeus.resources.Period[]"
 abstract="false"
 native="false"
 synchronized="false"
 static="false"
 final="false"
 deprecated="not deprecated"
 visibility="public"
>
<exception name="ResponseException" type="com.amadeus.exceptions.ResponseException">
</exception>
</method>
<field name="ARRIVING"
 type="java.lang.String"
 transient="false"
 volatile="false"
 value="&quot;ARRIVING&quot;"
 static="true"
 final="true"
 deprecated="not deprecated"
 visibility="public"
>
</field>
<field name="DEPARTING"
 type="java.lang.String"
 transient="false"
 volatile="false"
 value="&quot;DEPARTING&quot;"
 static="true"
 final="true"
 deprecated="not deprecated"
 visibility="public"
>
</field>
</class>
<class name="Traveled"
 extends="java.lang.Object"
 abstract="false"
 static="false"
 final="false"
 deprecated="not deprecated"
 visibility="public"
>
<method name="get"
 return="com.amadeus.resources.AirTraffic[]"
 abstract="false"
 native="false"
 synchronized="false"
 static="false"
 final="false"
 deprecated="not deprecated"
 visibility="public"
>
<parameter name="params" type="com.amadeus.Params">
</parameter>
<exception name="ResponseException" type="com.amadeus.exceptions.ResponseException">
</exception>
</method>
<method name="get"
 return="com.amadeus.resources.AirTraffic[]"
 abstract="false"
 native="false"
 synchronized="false"
 static="false"
 final="false"
 deprecated="not deprecated"
 visibility="public"
>
<exception name="ResponseException" type="com.amadeus.exceptions.ResponseException">
</exception>
</method>
</class>
</package>
</api>
